bandas.py
bandas-0.1.dist-info/METADATA
bandas-0.1.dist-info/WHEEL
bandas-0.1.dist-info/top_level.txt
bandas-0.1.dist-info/RECORD
