Metadata-Version: 2.1
Name: bandas
Version: 0.1
Summary: Códido para extrair estrutura de bandas a partir de um cálculo nscf, do pacote Quantum-Espresso v>6.4.
Author-email: "Marcio F. Santos" <marciofs600@gmail.com>
Classifier: Programming Language :: Python :: 3
Classifier: License :: OSI Approved :: MIT License
Classifier: Operating System :: OS Independent
Requires-Python: >=3.6
Requires-Dist: numpy (>=1.20.0)
